sims_reia/__init__.py
sims_reia/encoder.py
sims_reia/ReiaFile.py
sims_reia/ReiaFrame.py
sims_reia-0.1.2.dist-info/WHEEL
sims_reia-0.1.2.dist-info/METADATA
sims_reia-0.1.2.dist-info/RECORD
