Metadata-Version: 2.1
Name: sims-reia
Version: 0.1.2
Summary: 
Home-page: https://github.com/ammaraskar/SimsReiaParser
Author: Ammar Askar
Author-email: ammar@ammaraskar.com
Requires-Python: >=3.8,<4.0
Classifier: Programming Language :: Python :: 3
Classifier: Programming Language :: Python :: 3.8
Classifier: Programming Language :: Python :: 3.9
Classifier: Programming Language :: Python :: 3.10
Classifier: Programming Language :: Python :: 3.11
Requires-Dist: pillow (>=9.3.0,<10.0.0)
Project-URL: Repository, https://github.com/ammaraskar/SimsReiaParser/tree/main/SimsReiaPy
